[
  {
    "council": "Bolton",
    "field": "reserves",
    "pdf": "statement-of-accounts-2024-25.pdf",
    "page": 22,
    "value": "Balance at 31 March 2025 carried forward 250,348"
  },
  {
    "council": "Bolton",
    "field": "chief_executive",
    "pdf": "statement-of-accounts-2024-25.pdf",
    "page": 105,
    "value": "Sue Johnson"
  },
  {
    "council": "Bolton",
    "field": "chief_executive_salary",
    "pdf": "statement-of-accounts-2024-25.pdf",
    "page": 105,
    "value": "Sue Johnson 195,712"
  },
  {
    "council": "Bolton",
    "field": "total_allowances_cost",
    "pdf": "statement-of-accounts-2024-25.pdf",
    "page": 104,
    "value": "Allowances 889"
  }
]
